esphome/__init__.py
esphome/__main__.py
esphome/automation.py
esphome/codegen.py
esphome/config.py
esphome/config_helpers.py
esphome/config_validation.py
esphome/const.py
esphome/coroutine.py
esphome/cpp_generator.py
esphome/cpp_helpers.py
esphome/cpp_types.py
esphome/espota2.py
esphome/final_validate.py
esphome/git.py
esphome/helpers.py
esphome/loader.py
esphome/log.py
esphome/mqtt.py
esphome/pins.py
esphome/platformio_api.py
esphome/schema_extractors.py
esphome/storage_json.py
esphome/types.py
esphome/util.py
esphome/voluptuous_schema.py
esphome/vscode.py
esphome/wizard.py
esphome/writer.py
esphome/yaml_util.py
esphome/zeroconf.py
esphome/components/__init__.py
esphome/components/a4988/__init__.py
esphome/components/a4988/a4988.cpp
esphome/components/a4988/a4988.h
esphome/components/a4988/stepper.py
esphome/components/ac_dimmer/__init__.py
esphome/components/ac_dimmer/ac_dimmer.cpp
esphome/components/ac_dimmer/ac_dimmer.h
esphome/components/ac_dimmer/output.py
esphome/components/adalight/__init__.py
esphome/components/adalight/adalight_light_effect.cpp
esphome/components/adalight/adalight_light_effect.h
esphome/components/adc/__init__.py
esphome/components/adc/adc_sensor.cpp
esphome/components/adc/adc_sensor.h
esphome/components/adc/sensor.py
esphome/components/addressable_light/__init__.py
esphome/components/addressable_light/addressable_light_display.cpp
esphome/components/addressable_light/addressable_light_display.h
esphome/components/addressable_light/display.py
esphome/components/ade7953/__init__.py
esphome/components/ade7953/ade7953.cpp
esphome/components/ade7953/ade7953.h
esphome/components/ade7953/sensor.py
esphome/components/ads1115/__init__.py
esphome/components/ads1115/ads1115.cpp
esphome/components/ads1115/ads1115.h
esphome/components/ads1115/sensor.py
esphome/components/aht10/__init__.py
esphome/components/aht10/aht10.cpp
esphome/components/aht10/aht10.h
esphome/components/aht10/sensor.py
esphome/components/airthings_ble/__init__.py
esphome-2022.8.3.dist-info/LICENSE
esphome-2022.8.3.dist-info/METADATA
esphome-2022.8.3.dist-info/WHEEL
esphome-2022.8.3.dist-info/entry_points.txt
esphome-2022.8.3.dist-info/top_level.txt
esphome-2022.8.3.dist-info/RECORD
