Metadata-Version: 2.1
Name: esphome
Version: 2022.8.3
Summary: Make creating custom firmwares for ESP32/ESP8266 super easy.
Home-page: https://github.com/esphome/esphome
Download-URL: https://github.com/esphome/esphome/archive/2022.8.3.zip
Author: ESPHome
Author-email: esphome@nabucasa.com
License: MIT
Project-URL: Bug Tracker, https://github.com/esphome/issues/issues
Project-URL: Feature Request Tracker, https://github.com/esphome/feature-requests/issues
Project-URL: Source Code, https://github.com/esphome/esphome
Project-URL: Documentation, https://esphome.io
Project-URL: Twitter, https://twitter.com/esphome_
Keywords: home,automation
Platform: any
Classifier: Environment :: Console
Classifier: Intended Audience :: Developers
Classifier: Intended Audience :: End Users/Desktop
Classifier: License :: OSI Approved :: MIT License
Classifier: Programming Language :: C++
Classifier: Programming Language :: Python :: 3
Classifier: Topic :: Home Automation
Requires-Python: >=3.8,<4.0
License-File: LICENSE
Requires-Dist: voluptuous (==0.13.1)
Requires-Dist: PyYAML (==6.0)
Requires-Dist: paho-mqtt (==1.6.1)
Requires-Dist: colorama (==0.4.5)
Requires-Dist: tornado (==6.1)
Requires-Dist: tzlocal (==4.2)
Requires-Dist: tzdata (>=2021.1)
Requires-Dist: pyserial (==3.5)
Requires-Dist: platformio (==6.0.2)
Requires-Dist: esptool (==3.3.1)
Requires-Dist: click (==8.1.3)
Requires-Dist: esphome-dashboard (==20220508.0)
Requires-Dist: aioesphomeapi (==10.11.0)
Requires-Dist: zeroconf (==0.39.0)
Requires-Dist: kconfiglib (==13.7.1)
